micropython_icg20660/__init__.py
micropython_icg20660/i2c_helpers.py
micropython_icg20660/icg20660.py
micropython_icg20660-0.1.0.dist-info/LICENSE
micropython_icg20660-0.1.0.dist-info/METADATA
micropython_icg20660-0.1.0.dist-info/WHEEL
micropython_icg20660-0.1.0.dist-info/top_level.txt
micropython_icg20660-0.1.0.dist-info/RECORD
