Metadata-Version: 2.1
Name: micropython-icg20660
Version: 0.1.0
Summary: MicroPython Driver for the TDK ICG20660 Accelerometer/Gyro sensor
Author-email: JDM <xxyx@mailmeto.mozmail.com>
License: MIT
Project-URL: Homepage, https://github.com/jposada202020/MicroPython_ICG20660
Keywords: sensor,micropython,icg20660,micropython,driver,sensor,tdk,icg20660,acelerometer,gyro
Classifier: Intended Audience :: Developers
Classifier: Topic :: Software Development :: Libraries
Classifier: Topic :: Software Development :: Embedded Systems
Classifier: Topic :: System :: Hardware
Classifier: License :: OSI Approved :: MIT License
Classifier: Programming Language :: Python :: Implementation :: MicroPython
License-File: LICENSE
